Metadata-Version: 1.0
Name: distributions-dsmittal
Version: 0.1
Summary: Gaussian & Binomial distributions
Home-page: UNKNOWN
Author: Devanshi Mittal
Author-email: UNKNOWN
License: UNKNOWN
Platform: UNKNOWN
